Metadata-Version: 1.1
Name: BigJob2
Version: 0.54.post73
Summary: P* Pilot-Job Implementation based on SAGA-Python
Home-page: https://github.com/saga-project/BigJob
Author: Andre Luckow, et al.
Author-email: aluckow@cct.lsu.edu
License: UNKNOWN
Platform: Unix
Platform: Linux
Platform: Mac OS
Classifier: Development Status :: 5 - Production/Stable
Classifier: Programming Language :: Python
Classifier: Environment :: Console
Classifier: Topic :: Utilities
